pn_sequence/__init__.py
pn_cho-0.1.0.dist-info/COPYING
pn_cho-0.1.0.dist-info/COPYING.LESSER
pn_cho-0.1.0.dist-info/METADATA
pn_cho-0.1.0.dist-info/WHEEL
pn_cho-0.1.0.dist-info/RECORD
