Metadata-Version: 2.3
Name: pn-cho
Version: 0.1.0
Summary: A library for testing pseudo-noise (PN) sequences.
Author: pokeghost
Author-email: pokeghost@disroot.org
Requires-Python: >=3.9
Classifier: Programming Language :: Python :: 3
Classifier: Programming Language :: Python :: 3.9
Classifier: Programming Language :: Python :: 3.10
Classifier: Programming Language :: Python :: 3.11
Classifier: Programming Language :: Python :: 3.12
Classifier: Programming Language :: Python :: 3.13
